functionapplydict/README.MD
functionapplydict/__init__.py
functionapplydict/requirements.txt
functionapplydict/thirdparty.json
functionapplydict-0.10.dist-info/LICENSE.rst
functionapplydict-0.10.dist-info/METADATA
functionapplydict-0.10.dist-info/WHEEL
functionapplydict-0.10.dist-info/top_level.txt
functionapplydict-0.10.dist-info/RECORD
