Metadata-Version: 2.1
Name: functionapplydict
Version: 0.10
Summary: Applies a given function to the values of a nested dictionary
Home-page: https://github.com/hansalemaos/functionapplydict
Author: Johannes Fischer
Author-email: aulasparticularesdealemaosp@gmail.com
License: MIT
Keywords: nested,dict,apply
Classifier: Development Status :: 4 - Beta
Classifier: Programming Language :: Python :: 3 :: Only
Classifier: Programming Language :: Python :: 3.10
Classifier: Topic :: Software Development :: Libraries :: Python Modules
Classifier: Topic :: Utilities
License-File: LICENSE.rst
Requires-Dist: deepcopyall
Requires-Dist: flatten-any-dict-iterable-or-whatsoever
Requires-Dist: isiter
Requires-Dist: multikeyiterdict
